gcGroupbyExtension/__init__.py
gcGroupbyExtension_gcalmettes-0.0.3.dist-info/LICENSE
gcGroupbyExtension_gcalmettes-0.0.3.dist-info/METADATA
gcGroupbyExtension_gcalmettes-0.0.3.dist-info/WHEEL
gcGroupbyExtension_gcalmettes-0.0.3.dist-info/top_level.txt
gcGroupbyExtension_gcalmettes-0.0.3.dist-info/RECORD
