Metadata-Version: 2.1
Name: gcGroupbyExtension-gcalmettes
Version: 0.0.3
Summary: Allows to construct a pipeline of functions to be applied independently on the groups of a groupby object.
Home-page: https://github.com/gcalmettes/pandas-groupby-apply-chaining-extension
Author: Guillaume Calmettes
Author-email: gcalmettes@g.ucla.edu
License: UNKNOWN
Platform: UNKNOWN
Classifier: Programming Language :: Python :: 3
Classifier: License :: OSI Approved :: MIT License
Classifier: Operating System :: OS Independent
